LICENSE
README.md
setup.py
drf_util/__init__.py
drf_util/config.py
drf_util/decorators.py
drf_util/elastic.py
drf_util/exceptions.py
drf_util/fields.py
drf_util/filters.py
drf_util/functions.py
drf_util/lookups.py
drf_util/managers.py
drf_util/middlewares.py
drf_util/mixins.py
drf_util/models.py
drf_util/pagination.py
drf_util/serializers.py
drf_util/tests.py
drf_util/utils.py
drf_util/validators.py
drf_util/variables.py
drf_util/views.py
drf_util.egg-info/PKG-INFO
drf_util.egg-info/SOURCES.txt
drf_util.egg-info/dependency_links.txt
drf_util.egg-info/not-zip-safe
drf_util.egg-info/requires.txt
drf_util.egg-info/top_level.txt